woodelf/__init__.py
woodelf/cube_metric.py
woodelf/decision_trees_ensemble.py
woodelf/direct_computation.py
woodelf/explainer.py
woodelf/high_depth_woodelf.py
woodelf/parse_models.py
woodelf/path_to_matrices.py
woodelf/simple_woodelf.py
woodelf/utils.py
woodelf/vectorized_linear_tree_shap.py
woodelf_explainer-0.2.8.dist-info/licenses/LICENSE
woodelf_explainer-0.2.8.dist-info/METADATA
woodelf_explainer-0.2.8.dist-info/WHEEL
woodelf_explainer-0.2.8.dist-info/top_level.txt
woodelf_explainer-0.2.8.dist-info/RECORD
