Metadata-Version: 2.4
Name: woodelf_explainer
Version: 0.2.8
Summary: Fast explainability algorithms for tree ensembles
Author-email: Ron Wettenstein <ron-wettenstein@gmail.com>
License: The MIT License (MIT)
Project-URL: Homepage, https://github.com/ron-wettenstein/woodelf
Requires-Python: >=3.9
License-File: LICENSE
Requires-Dist: numpy
Requires-Dist: pandas
Requires-Dist: scipy
Requires-Dist: shap
Provides-Extra: test
Requires-Dist: pytest; extra == "test"
Requires-Dist: xgboost>=2.0; extra == "test"
Requires-Dist: scikit-learn; extra == "test"
Requires-Dist: shap; extra == "test"
Provides-Extra: gpu
Requires-Dist: cupy; extra == "gpu"
Dynamic: license-file
